<?xml version="1.0" encoding="UTF-8"?>
<objects serializationModel="Studio.02.02.00">
	<object class="AudioFile" id="{c27f8e6e-5044-4cc2-a541-45aa9df7dd48}">
		<property name="assetPath">
			<value>ANIMAL_AFRICAN_WILD_DOG_WHINING03.WAV</value>
		</property>
		<property name="frequencyInKHz">
			<value>48</value>
		</property>
		<property name="channelCount">
			<value>2</value>
		</property>
		<property name="length">
			<value>0.8169791666666667</value>
		</property>
		<relationship name="masterAssetFolder">
			<destination>{eb40ce51-15be-4a0d-8cfb-9494e01aba2a}</destination>
		</relationship>
	</object>
</objects>
